ctadl/VERSION
ctadl/__init__.py
ctadl/models.py
ctadl/models/ctadl-model-generator.schema.json
ctadl/models/jadx/default-index.json
ctadl/models/jadx/default-query.json
ctadl/models/pcode/default-index.json
ctadl/models/pcode/default-query.json
ctadl/models/taint-front/default-index.json
ctadl/models/taint-front/default-query.json
ctadl/souffle-logic/config.dl
ctadl/souffle-logic/ctadl_ir_types.dl
ctadl/souffle-logic/ctadl_schema.dl
ctadl/souffle-logic/export.dl
ctadl/souffle-logic/functors.cpp
ctadl/souffle-logic/graph_schema.dl
ctadl/souffle-logic/imports.dl
ctadl/souffle-logic/macros.dl
ctadl/souffle-logic/taint_schema.dl
ctadl/souffle-logic/graph/access_path.dl
ctadl/souffle-logic/graph/callgraph.dl
ctadl/souffle-logic/graph/dataflow.dl
ctadl/souffle-logic/graph/dataflow_graph.dl
ctadl/souffle-logic/graph/declarations.dl
ctadl/souffle-logic/graph/export.dl
ctadl/souffle-logic/graph/fieldprop.dl
ctadl/souffle-logic/graph/fieldprop_ref.dl
ctadl/souffle-logic/graph/globals.dl
ctadl/souffle-logic/graph/hybrid_inlining.dl
ctadl/souffle-logic/graph/import.dl
ctadl/souffle-logic/graph/star.dl
ctadl/souffle-logic/graph/slice/bidi.dl
ctadl/souffle-logic/graph/slice/callee.dl
ctadl/souffle-logic/graph/slice/declarations.dl
ctadl/souffle-logic/graph/slice/taint.dl
ctadl/souffle-logic/information-flow/declarations.dl
ctadl/souffle-logic/information-flow/export.dl
ctadl/souffle-logic/information-flow/java-transfer.dl
ctadl/souffle-logic/information-flow/query.dl
ctadl/souffle-logic/jadx/android-intents.dl
ctadl/souffle-logic/jadx/customquery.dl
ctadl/souffle-logic/jadx/export.dl
ctadl/souffle-logic/jadx/importdb.dl
ctadl/souffle-logic/jadx/index.dl
ctadl/souffle-logic/jadx/jadx-fact-decls.dl
ctadl/souffle-logic/jadx/jadx-fact-imports.dl
ctadl/souffle-logic/jadx/jadx_lang.dl
ctadl/souffle-logic/pcode/ExportPCodeForCTADL.java
ctadl/souffle-logic/pcode/analyzeHeadlessBigMem
ctadl/souffle-logic/pcode/analyzeHeadlessBigMem.bat
ctadl/souffle-logic/pcode/analyze_headless.sh
ctadl-0.11.2.dist-info/LICENSE.txt
ctadl-0.11.2.dist-info/METADATA
ctadl-0.11.2.dist-info/WHEEL
ctadl-0.11.2.dist-info/top_level.txt
ctadl-0.11.2.dist-info/RECORD
