Metadata-Version: 2.1
Name: ctadl
Version: 0.11.2
Summary: CTADL Static Taint Analyzer
Home-page: https://github.com/sandialabs/ctadl
Project-URL: Bug Tracker, https://github.com/sandialabs/ctadl/issues
Classifier: Programming Language :: Python :: 3.9
Classifier: Environment :: Console
Classifier: License :: OSI Approved :: Apache Software License
Classifier: Operating System :: POSIX
Requires-Python: >=3.9
License-File: LICENSE.txt
Requires-Dist: json5
Provides-Extra: ghidra-fact-generator
Requires-Dist: ctadl-ghidra-fact-generator-plugin (>=0.0.2) ; extra == 'ghidra-fact-generator'
Provides-Extra: jadx-fact-generator
Requires-Dist: ctadl-jadx-fact-generator-plugin (>=0.6.2) ; extra == 'jadx-fact-generator'
Provides-Extra: networkx-exporter
Requires-Dist: ctadl-networkx-export-plugin (>=0.0.1) ; extra == 'networkx-exporter'
Provides-Extra: taint-front-fact-generator
Requires-Dist: ctadl-taint-front-fact-generator-plugin (>=0.0.2) ; extra == 'taint-front-fact-generator'
